vehicle_ml/__init__.py
vehicle_ml/logger.py
vehicle_ml/trainer.py
vehicle_ml/trainer_utils.py
vehicle_ml/data/__init__.py
vehicle_ml/data/clean_data.py
vehicle_ml/data/explore_data.py
vehicle_ml/data/ingest_data.py
vehicle_ml/data/split_data.py
vehicle_ml/feature/__init__.py
vehicle_ml/feature/date_feature.py
vehicle_ml/feature/local_store.py
vehicle_ml/feature/registry.py
vehicle_ml/feature/store.py
vehicle_ml/feature/tabular_feature.py
vehicle_ml/feature/ts_feature.py
vehicle_ml/feature/value_transform.py
vehicle_ml/metrics/__init__.py
vehicle_ml/metrics/classification.py
vehicle_ml/metrics/regression.py
vehicle_ml/utils/__init__.py
vehicle_ml/utils/misc.py
vehicle_ml/utils/mlflow_utils.py
vehicle_ml-0.0.1.dist-info/licenses/LICENSE
vehicle_ml-0.0.1.dist-info/METADATA
vehicle_ml-0.0.1.dist-info/WHEEL
vehicle_ml-0.0.1.dist-info/top_level.txt
vehicle_ml-0.0.1.dist-info/RECORD
