Metadata-Version: 2.4
Name: vehicle_ml
Version: 0.0.1
Summary: Forecasting Vehicle Sales with XGBoost: A Modern Approach to Predictive Modeling
Author-email: Hongying Yue <yuehongyingyhy@gmail.com>
License-File: LICENSE
Requires-Dist: pyyaml
Requires-Dist: numpy
Requires-Dist: pandas
Requires-Dist: scikit-learn
Requires-Dist: xgboost
Requires-Dist: matplotlib
Requires-Dist: psutil
Provides-Extra: dev
Requires-Dist: pre-commit; extra == "dev"
Requires-Dist: black; extra == "dev"
Requires-Dist: ruff; extra == "dev"
Requires-Dist: pylint; extra == "dev"
Requires-Dist: isort; extra == "dev"
Dynamic: license-file
